darkphoenixAES/AES.py
darkphoenixAES/Attack.py
darkphoenixAES/Encoding.py
darkphoenixAES/Exception.py
darkphoenixAES/ExtractEncoding.py
darkphoenixAES/FaultPositionValidator.py
darkphoenixAES/MeetITM.py
darkphoenixAES/MultTable.py
darkphoenixAES/Step1.py
darkphoenixAES/Step2.py
darkphoenixAES/Step3.py
darkphoenixAES/Step3_sage.py
darkphoenixAES/Step4.py
darkphoenixAES/Step5.py
darkphoenixAES/Utils.py
darkphoenixAES/WhiteBoxedAES.py
darkphoenixAES/WhiteBoxedAESProxy.py
darkphoenixAES/__init__.py
darkphoenixAES/__main__.py
darkphoenixAES/test/AESEncoded.py
darkphoenixAES/test/WhiteBoxedAESAutoTest.py
darkphoenixAES/test/WhiteBoxedAESTest.py
darkphoenixAES/test/test_AES.py
darkphoenixAES/test/test_Attack.py
darkphoenixAES/test/test_Encoding.py
darkphoenixAES/test/test_WhiteBoxedAESProxy.py
darkphoenixAES-1.0.0.dist-info/LICENSE.txt
darkphoenixAES-1.0.0.dist-info/METADATA
darkphoenixAES-1.0.0.dist-info/WHEEL
darkphoenixAES-1.0.0.dist-info/top_level.txt
darkphoenixAES-1.0.0.dist-info/RECORD
