Metadata-Version: 2.1
Name: darkphoenixAES
Version: 1.0.0
Summary: DarkPhoenix is a tool to perform differential fault analysis attacks (DFA) against AES whiteboxes with external encodings
Author: Nicolas Surbayrole, Philippe Teuwen
License: apache2
Project-URL: Source, https://github.com/SideChannelMarvels/DarkPhoenix
Classifier: Development Status :: 3 - Alpha
Classifier: License :: OSI Approved :: Apache Software License
Classifier: Programming Language :: Python
Classifier: Operating System :: OS Independent
Classifier: Topic :: Security :: Cryptography
Classifier: Intended Audience :: Science/Research
Requires-Python: >=3.7
License-File: LICENSE.txt
Requires-Dist: tqdm
